py_pal/__init__.py
py_pal/__main__.py
py_pal/datagen.py
py_pal/util.py
py_pal/settings.py
py_pal/export.py
py_pal/core.py
py_pal/data_collection/proxy.c
py_pal/data_collection/proxy.cpython-37m-x86_64-linux-gnu.so
py_pal/data_collection/metric.h
py_pal/data_collection/__init__.py
py_pal/data_collection/tracer.cpython-37m-x86_64-linux-gnu.so
py_pal/data_collection/metric.pxd
py_pal/data_collection/arguments.pxd
py_pal/data_collection/proxy.pyx
py_pal/data_collection/metric.c
py_pal/data_collection/opcode_metric.html
py_pal/data_collection/opcode_metric.pxd
py_pal/data_collection/arguments.pyx
py_pal/data_collection/tracer.pyx
py_pal/data_collection/proxy.pxd
py_pal/data_collection/opcode_metric.cpython-37m-x86_64-linux-gnu.so
py_pal/data_collection/tracer.pxd
py_pal/data_collection/metric.pyx
py_pal/data_collection/opcode_metric.c
py_pal/data_collection/tracer.c
py_pal/data_collection/metric.cpython-37m-x86_64-linux-gnu.so
py_pal/data_collection/arguments.cpython-37m-x86_64-linux-gnu.so
py_pal/data_collection/metric.html
py_pal/data_collection/tracer.html
py_pal/data_collection/arguments.c
py_pal/data_collection/proxy.html
py_pal/data_collection/opcode_metric.pyx
py_pal/analysis/__init__.py
py_pal/analysis/estimator.py
py_pal/analysis/complexity.py
py_pal/__pycache__/__init__.cpython-37.pyc
py_pal-1.3.0.dist-info/METADATA
py_pal-1.3.0.dist-info/RECORD
py_pal-1.3.0.dist-info/LICENSE
py_pal-1.3.0.dist-info/top_level.txt
py_pal-1.3.0.dist-info/WHEEL
py_pal-1.3.0.dist-info/entry_points.txt
