Metadata-Version: 2.1
Name: py-pal
Version: 1.3.0
Summary: Estimate Asymptotic Runtime Complexity from Bytecode executions
Home-page: https://gitlab.lukasjung.de/root/py-pal
Author: Lukas Jung
Author-email: mail@lukasjung.de
License: MIT
Project-URL: Documentation, https://py-pal.readthedocs.io/en/latest/
Platform: UNKNOWN
Classifier: Development Status :: 4 - Beta
Classifier: Intended Audience :: Developers
Classifier: License :: OSI Approved :: MIT License
Classifier: Operating System :: Unix
Classifier: Operating System :: POSIX
Classifier: Operating System :: Microsoft :: Windows
Classifier: Programming Language :: Python :: 3.7
Classifier: Programming Language :: Python :: 3.8
Classifier: Programming Language :: Python :: 3.9
Classifier: Programming Language :: Python :: Implementation :: CPython
Classifier: Topic :: Utilities
Classifier: Topic :: Software Development :: Debuggers
Requires-Python: >=3.7
